MANIFEST.in
README.rst
setup.py
test.py
docs/CREDITS.txt
docs/HISTORY.rst
docs/LICENSE.txt
src/roughrider/__init__.py
src/roughrider.predicate.egg-info/PKG-INFO
src/roughrider.predicate.egg-info/SOURCES.txt
src/roughrider.predicate.egg-info/dependency_links.txt
src/roughrider.predicate.egg-info/namespace_packages.txt
src/roughrider.predicate.egg-info/not-zip-safe
src/roughrider.predicate.egg-info/requires.txt
src/roughrider.predicate.egg-info/top_level.txt
src/roughrider/predicate/__init__.py
src/roughrider/predicate/decorator.py
src/roughrider/predicate/errors.c
src/roughrider/predicate/errors.pyx
src/roughrider/predicate/types.py
src/roughrider/predicate/utils.c
src/roughrider/predicate/utils.pyx
src/roughrider/predicate/validators.py
tests/test_decorator.py
tests/test_errors.py
tests/test_http_errors.py
tests/test_validators.py