Metadata-Version: 2.1
Name: roughrider.predicate
Version: 0.3.1
Summary: Pure python predicate/guard/validation system.
Home-page: http://gitweb.dolmen-project.org
Author: Souheil CHELFOUH
Author-email: trollfot@gmail.com
License: ZPL
Download-URL: http://pypi.python.org/pypi/roughrider.predicate
Platform: UNKNOWN
Classifier: Environment :: Web Environment
Classifier: Intended Audience :: Developers
Classifier: License :: OSI Approved :: Zope Public License
Classifier: Programming Language :: Python :: 3.8
Classifier: Programming Language :: Python :: 3.9
Classifier: Programming Language :: Python :: 3.10
Provides-Extra: test
